[
    {
        "id": 1,
        "titre": "titre",
        "img": "url....",
        "description": "sfeks lkselfkselfks lfkselfk skflsefkls lsefkls fkelfksl efkslf elf seklfks lfek slkselfk slefkslf selfk",
        "github": "url...",
        "projet": "url....",
        "outil": [
            "php", "css"
        ]
    },
    {
        "id": 2,
        "titre": "titre",
        "img": "url....",
        "description": "sfeks lkselfkselfks lfkselfk skflsefkls lsefkls fkelfksl efkslf elf seklfks lfek slkselfk slefkslf selfk",
        "github": "url...",
        "projet": "url....",
        "outil": [
            "php", "css"
        ]
    },
    {
        "id": 3,
        "titre": "titre",
        "img": "url....",
        "description": "sfeks lkselfkselfks lfkselfk skflsefkls lsefkls fkelfksl efkslf elf seklfks lfek slkselfk slefkslf selfk",
        "github": "url...",
        "projet": "url....",
        "outil": [
            "php", "css"
        ]
    }
]